LICENSE
README.md
setup.py
autogaita/__init__.py
autogaita/__main__.py
autogaita.egg-info/PKG-INFO
autogaita.egg-info/SOURCES.txt
autogaita.egg-info/dependency_links.txt
autogaita.egg-info/requires.txt
autogaita.egg-info/top_level.txt
autogaita/batchrun_scripts/__init__.py
autogaita/batchrun_scripts/dlc_multirun.py
autogaita/batchrun_scripts/dlc_singlerun.py
autogaita/batchrun_scripts/group_dlcrun.py
autogaita/batchrun_scripts/group_universal3Drun.py
autogaita/batchrun_scripts/sleap_singlerun.py
autogaita/batchrun_scripts/universal3D_multirun.py
autogaita/batchrun_scripts/universal3D_singlerun.py
autogaita/common2D/__init__.py
autogaita/common2D/common2D_1_preparation.py
autogaita/common2D/common2D_2_sc_extraction.py
autogaita/common2D/common2D_3_analysis.py
autogaita/common2D/common2D_4_plots.py
autogaita/common2D/common2D_constants.py
autogaita/common2D/common2D_utils.py
autogaita/dlc/__init__.py
autogaita/dlc/dlc_main.py
autogaita/group/__init__.py
autogaita/group/group_1_preparation.py
autogaita/group/group_2_data_processing.py
autogaita/group/group_3_PCA.py
autogaita/group/group_4_stats.py
autogaita/group/group_5_plots.py
autogaita/group/group_constants.py
autogaita/group/group_main.py
autogaita/group/group_utils.py
autogaita/gui/__init__.py
autogaita/gui/common2D_advanced_config_gui.py
autogaita/gui/common2D_columninfo_gui.py
autogaita/gui/common2D_gui_constants.py
autogaita/gui/common2D_gui_utils.py
autogaita/gui/common2D_main_gui.py
autogaita/gui/common2D_run_and_done_gui.py
autogaita/gui/dlc_gui.py
autogaita/gui/dlc_gui_config.json
autogaita/gui/first_level_gui_utils.py
autogaita/gui/gaita_widgets.py
autogaita/gui/group_gui.py
autogaita/gui/group_gui_config.json
autogaita/gui/gui_constants.py
autogaita/gui/gui_utils.py
autogaita/gui/main_gui.py
autogaita/gui/sleap_gui.py
autogaita/gui/sleap_gui_config.json
autogaita/gui/universal3D_gui.py
autogaita/gui/universal3D_gui_config.json
autogaita/resources/__init__.py
autogaita/resources/constants.py
autogaita/resources/folder.png
autogaita/resources/icon.icns
autogaita/resources/icon.ico
autogaita/resources/logo.png
autogaita/resources/pic_to_demo_for_repo.png
